<LanguagePoiConfiguration xmlns:xsi="http://www.w3.org/2001/XMLSchema-instance" xsi:noNamespaceSchemaLocation="xsd/locale/LanguagePoiConfiguration.xsd" version="1">
<!--Alphabetically sorted setup category definitions for each fuel type, will be reloaded after language change-->
	<SetupCategoryDefinition>
		<PoiCategoryMapping fueltype="default">
			<PoiCategoryRef>135</PoiCategoryRef>
			<!-- Aardgas tankstations -->
			<PoiCategoryRef>50</PoiCategoryRef>
			<!-- Ambassades -->
			<PoiCategoryRef>23</PoiCategoryRef>
			<!-- Apotheken -->
			<PoiCategoryRef>1</PoiCategoryRef>
			<!-- Autostadt -->
			<PoiCategoryRef>15</PoiCategoryRef>
			<!-- Autoverhuur -->
			<PoiCategoryRef>14</PoiCategoryRef>
			<!-- Autowegaf-/opritten -->
			<PoiCategoryRef>45</PoiCategoryRef>
			<!-- Banken -->
			<PoiCategoryRef>47</PoiCategoryRef>
			<!-- Bedrijven -->
			<PoiCategoryRef>36</PoiCategoryRef>
			<!-- Beeldende kunsten -->
			<PoiCategoryRef>49</PoiCategoryRef>
			<!-- Bestuur en beheer -->
			<PoiCategoryRef>33</PoiCategoryRef>
			<!-- Bezienswaardigheden -->
			<PoiCategoryRef>34</PoiCategoryRef>
			<!-- Bioscopen -->
			<PoiCategoryRef>42</PoiCategoryRef>
			<!-- Bootsport -->
			<PoiCategoryRef>18</PoiCategoryRef>
			<!-- Busstations -->
			<PoiCategoryRef>26</PoiCategoryRef>
			<!-- Cafés -->
			<PoiCategoryRef>35</PoiCategoryRef>
			<!-- Casino's -->
			<PoiCategoryRef>48</PoiCategoryRef>
			<!-- Congrescentra -->
			<PoiCategoryRef>29</PoiCategoryRef>
			<!-- Elektronica -->
			<PoiCategoryRef>38</PoiCategoryRef>
			<!-- Gedenktekens -->
			<PoiCategoryRef>25</PoiCategoryRef>
			<!-- Geldautomaten -->
			<PoiCategoryRef>22</PoiCategoryRef>
			<!-- Geneeskundige diensten -->
			<PoiCategoryRef>53</PoiCategoryRef>
			<!-- Godshuizen -->
			<PoiCategoryRef>41</PoiCategoryRef>
			<!-- Golfsport -->
			<PoiCategoryRef>10</PoiCategoryRef>
			<!-- Grensovergangen -->
			<PoiCategoryRef>8</PoiCategoryRef>
			<!-- Hotels en motels -->
			<PoiCategoryRef>54</PoiCategoryRef>
			<!-- Kerkhoven -->
			<PoiCategoryRef>28</PoiCategoryRef>
			<!-- Kleding -->
			<PoiCategoryRef>134</PoiCategoryRef>
			<!-- Laadstations -->
			<PoiCategoryRef>136</PoiCategoryRef>
			<!-- LPG tankstation -->
			<PoiCategoryRef>37</PoiCategoryRef>
			<!-- Musea -->
			<PoiCategoryRef>31</PoiCategoryRef>
			<!-- Nachtleven -->
			<PoiCategoryRef>52</PoiCategoryRef>
			<!-- Onderwijsinstellingen -->
			<PoiCategoryRef>102</PoiCategoryRef>
			<!-- Parkeerplaatsen -->
			<PoiCategoryRef>32</PoiCategoryRef>
			<!-- Parken -->
			<PoiCategoryRef>20</PoiCategoryRef>
			<!-- Politie -->
			<PoiCategoryRef>46</PoiCategoryRef>
			<!-- Post -->
			<PoiCategoryRef>44</PoiCategoryRef>
			<!-- Pretparken -->
			<PoiCategoryRef>104</PoiCategoryRef>
			<!-- Restaurants -->
			<PoiCategoryRef>43</PoiCategoryRef>
			<!-- Skisport -->
			<PoiCategoryRef>39</PoiCategoryRef>
			<!-- Sportcentra -->
			<PoiCategoryRef>16</PoiCategoryRef>
			<!-- Stations -->
			<PoiCategoryRef>101</PoiCategoryRef>
			<!-- Tankstations -->
			<PoiCategoryRef>19</PoiCategoryRef>
			<!-- Toeristeninformatie -->
			<PoiCategoryRef>9</PoiCategoryRef>
			<!-- Veerboten en autotreinen -->
			<PoiCategoryRef>2</PoiCategoryRef>
			<!-- Vliegveld -->
			<PoiCategoryRef>11</PoiCategoryRef>
			<!-- VW dealers -->
			<PoiCategoryRef>12</PoiCategoryRef>
			<!-- VW service -->
			<PoiCategoryRef>7</PoiCategoryRef>
			<!-- Wegrestaurants -->
			<PoiCategoryRef>30</PoiCategoryRef>
			<!-- Wijnen en gedestilleerd -->
			<PoiCategoryRef>27</PoiCategoryRef>
			<!-- Winkelcentra -->
			<PoiCategoryRef>21</PoiCategoryRef>
			<!-- Ziekenhuis -->
		</PoiCategoryMapping>
		<PoiCategoryMapping fueltype="gasoline">
			<PoiCategoryRef>135</PoiCategoryRef>
			<!-- Aardgas tankstations -->
			<PoiCategoryRef>50</PoiCategoryRef>
			<!-- Ambassades -->
			<PoiCategoryRef>23</PoiCategoryRef>
			<!-- Apotheken -->
			<PoiCategoryRef>1</PoiCategoryRef>
			<!-- Autostadt -->
			<PoiCategoryRef>15</PoiCategoryRef>
			<!-- Autoverhuur -->
			<PoiCategoryRef>14</PoiCategoryRef>
			<!-- Autowegaf-/opritten -->
			<PoiCategoryRef>45</PoiCategoryRef>
			<!-- Banken -->
			<PoiCategoryRef>47</PoiCategoryRef>
			<!-- Bedrijven -->
			<PoiCategoryRef>36</PoiCategoryRef>
			<!-- Beeldende kunsten -->
			<PoiCategoryRef>49</PoiCategoryRef>
			<!-- Bestuur en beheer -->
			<PoiCategoryRef>33</PoiCategoryRef>
			<!-- Bezienswaardigheden -->
			<PoiCategoryRef>34</PoiCategoryRef>
			<!-- Bioscopen -->
			<PoiCategoryRef>42</PoiCategoryRef>
			<!-- Bootsport -->
			<PoiCategoryRef>18</PoiCategoryRef>
			<!-- Busstations -->
			<PoiCategoryRef>26</PoiCategoryRef>
			<!-- Cafés -->
			<PoiCategoryRef>35</PoiCategoryRef>
			<!-- Casino's -->
			<PoiCategoryRef>48</PoiCategoryRef>
			<!-- Congrescentra -->
			<PoiCategoryRef>29</PoiCategoryRef>
			<!-- Elektronica -->
			<PoiCategoryRef>38</PoiCategoryRef>
			<!-- Gedenktekens -->
			<PoiCategoryRef>25</PoiCategoryRef>
			<!-- Geldautomaten -->
			<PoiCategoryRef>22</PoiCategoryRef>
			<!-- Geneeskundige diensten -->
			<PoiCategoryRef>53</PoiCategoryRef>
			<!-- Godshuizen -->
			<PoiCategoryRef>41</PoiCategoryRef>
			<!-- Golfsport -->
			<PoiCategoryRef>10</PoiCategoryRef>
			<!-- Grensovergangen -->
			<PoiCategoryRef>8</PoiCategoryRef>
			<!-- Hotels en motels -->
			<PoiCategoryRef>54</PoiCategoryRef>
			<!-- Kerkhoven -->
			<PoiCategoryRef>28</PoiCategoryRef>
			<!-- Kleding -->
			<PoiCategoryRef>134</PoiCategoryRef>
			<!-- Laadstations -->
			<PoiCategoryRef>136</PoiCategoryRef>
			<!-- LPG tankstation -->
			<PoiCategoryRef>37</PoiCategoryRef>
			<!-- Musea -->
			<PoiCategoryRef>31</PoiCategoryRef>
			<!-- Nachtleven -->
			<PoiCategoryRef>52</PoiCategoryRef>
			<!-- Onderwijsinstellingen -->
			<PoiCategoryRef>102</PoiCategoryRef>
			<!-- Parkeerplaatsen -->
			<PoiCategoryRef>32</PoiCategoryRef>
			<!-- Parken -->
			<PoiCategoryRef>20</PoiCategoryRef>
			<!-- Politie -->
			<PoiCategoryRef>46</PoiCategoryRef>
			<!-- Post -->
			<PoiCategoryRef>44</PoiCategoryRef>
			<!-- Pretparken -->
			<PoiCategoryRef>104</PoiCategoryRef>
			<!-- Restaurants -->
			<PoiCategoryRef>43</PoiCategoryRef>
			<!-- Skisport -->
			<PoiCategoryRef>39</PoiCategoryRef>
			<!-- Sportcentra -->
			<PoiCategoryRef>16</PoiCategoryRef>
			<!-- Stations -->
			<PoiCategoryRef>101</PoiCategoryRef>
			<!-- Tankstations -->
			<PoiCategoryRef>19</PoiCategoryRef>
			<!-- Toeristeninformatie -->
			<PoiCategoryRef>9</PoiCategoryRef>
			<!-- Veerboten en autotreinen -->
			<PoiCategoryRef>2</PoiCategoryRef>
			<!-- Vliegveld -->
			<PoiCategoryRef>11</PoiCategoryRef>
			<!-- VW dealers -->
			<PoiCategoryRef>12</PoiCategoryRef>
			<!-- VW service -->
			<PoiCategoryRef>7</PoiCategoryRef>
			<!-- Wegrestaurants -->
			<PoiCategoryRef>30</PoiCategoryRef>
			<!-- Wijnen en gedestilleerd -->
			<PoiCategoryRef>27</PoiCategoryRef>
			<!-- Winkelcentra -->
			<PoiCategoryRef>21</PoiCategoryRef>
			<!-- Ziekenhuis -->
		</PoiCategoryMapping>
		<PoiCategoryMapping fueltype="diesel">
			<PoiCategoryRef>135</PoiCategoryRef>
			<!-- Aardgas tankstations -->
			<PoiCategoryRef>50</PoiCategoryRef>
			<!-- Ambassades -->
			<PoiCategoryRef>23</PoiCategoryRef>
			<!-- Apotheken -->
			<PoiCategoryRef>1</PoiCategoryRef>
			<!-- Autostadt -->
			<PoiCategoryRef>15</PoiCategoryRef>
			<!-- Autoverhuur -->
			<PoiCategoryRef>14</PoiCategoryRef>
			<!-- Autowegaf-/opritten -->
			<PoiCategoryRef>45</PoiCategoryRef>
			<!-- Banken -->
			<PoiCategoryRef>47</PoiCategoryRef>
			<!-- Bedrijven -->
			<PoiCategoryRef>36</PoiCategoryRef>
			<!-- Beeldende kunsten -->
			<PoiCategoryRef>49</PoiCategoryRef>
			<!-- Bestuur en beheer -->
			<PoiCategoryRef>33</PoiCategoryRef>
			<!-- Bezienswaardigheden -->
			<PoiCategoryRef>34</PoiCategoryRef>
			<!-- Bioscopen -->
			<PoiCategoryRef>42</PoiCategoryRef>
			<!-- Bootsport -->
			<PoiCategoryRef>18</PoiCategoryRef>
			<!-- Busstations -->
			<PoiCategoryRef>26</PoiCategoryRef>
			<!-- Cafés -->
			<PoiCategoryRef>35</PoiCategoryRef>
			<!-- Casino's -->
			<PoiCategoryRef>48</PoiCategoryRef>
			<!-- Congrescentra -->
			<PoiCategoryRef>29</PoiCategoryRef>
			<!-- Elektronica -->
			<PoiCategoryRef>38</PoiCategoryRef>
			<!-- Gedenktekens -->
			<PoiCategoryRef>25</PoiCategoryRef>
			<!-- Geldautomaten -->
			<PoiCategoryRef>22</PoiCategoryRef>
			<!-- Geneeskundige diensten -->
			<PoiCategoryRef>53</PoiCategoryRef>
			<!-- Godshuizen -->
			<PoiCategoryRef>41</PoiCategoryRef>
			<!-- Golfsport -->
			<PoiCategoryRef>10</PoiCategoryRef>
			<!-- Grensovergangen -->
			<PoiCategoryRef>8</PoiCategoryRef>
			<!-- Hotels en motels -->
			<PoiCategoryRef>54</PoiCategoryRef>
			<!-- Kerkhoven -->
			<PoiCategoryRef>28</PoiCategoryRef>
			<!-- Kleding -->
			<PoiCategoryRef>134</PoiCategoryRef>
			<!-- Laadstations -->
			<PoiCategoryRef>136</PoiCategoryRef>
			<!-- LPG tankstation -->
			<PoiCategoryRef>37</PoiCategoryRef>
			<!-- Musea -->
			<PoiCategoryRef>31</PoiCategoryRef>
			<!-- Nachtleven -->
			<PoiCategoryRef>52</PoiCategoryRef>
			<!-- Onderwijsinstellingen -->
			<PoiCategoryRef>102</PoiCategoryRef>
			<!-- Parkeerplaatsen -->
			<PoiCategoryRef>32</PoiCategoryRef>
			<!-- Parken -->
			<PoiCategoryRef>20</PoiCategoryRef>
			<!-- Politie -->
			<PoiCategoryRef>46</PoiCategoryRef>
			<!-- Post -->
			<PoiCategoryRef>44</PoiCategoryRef>
			<!-- Pretparken -->
			<PoiCategoryRef>104</PoiCategoryRef>
			<!-- Restaurants -->
			<PoiCategoryRef>43</PoiCategoryRef>
			<!-- Skisport -->
			<PoiCategoryRef>39</PoiCategoryRef>
			<!-- Sportcentra -->
			<PoiCategoryRef>16</PoiCategoryRef>
			<!-- Stations -->
			<PoiCategoryRef>101</PoiCategoryRef>
			<!-- Tankstations -->
			<PoiCategoryRef>19</PoiCategoryRef>
			<!-- Toeristeninformatie -->
			<PoiCategoryRef>9</PoiCategoryRef>
			<!-- Veerboten en autotreinen -->
			<PoiCategoryRef>2</PoiCategoryRef>
			<!-- Vliegveld -->
			<PoiCategoryRef>11</PoiCategoryRef>
			<!-- VW dealers -->
			<PoiCategoryRef>12</PoiCategoryRef>
			<!-- VW service -->
			<PoiCategoryRef>7</PoiCategoryRef>
			<!-- Wegrestaurants -->
			<PoiCategoryRef>30</PoiCategoryRef>
			<!-- Wijnen en gedestilleerd -->
			<PoiCategoryRef>27</PoiCategoryRef>
			<!-- Winkelcentra -->
			<PoiCategoryRef>21</PoiCategoryRef>
			<!-- Ziekenhuis -->
		</PoiCategoryMapping>
		<PoiCategoryMapping fueltype="cng">
			<PoiCategoryRef>135</PoiCategoryRef>
			<!-- Aardgas tankstations -->
			<PoiCategoryRef>50</PoiCategoryRef>
			<!-- Ambassades -->
			<PoiCategoryRef>23</PoiCategoryRef>
			<!-- Apotheken -->
			<PoiCategoryRef>1</PoiCategoryRef>
			<!-- Autostadt -->
			<PoiCategoryRef>15</PoiCategoryRef>
			<!-- Autoverhuur -->
			<PoiCategoryRef>14</PoiCategoryRef>
			<!-- Autowegaf-/opritten -->
			<PoiCategoryRef>45</PoiCategoryRef>
			<!-- Banken -->
			<PoiCategoryRef>47</PoiCategoryRef>
			<!-- Bedrijven -->
			<PoiCategoryRef>36</PoiCategoryRef>
			<!-- Beeldende kunsten -->
			<PoiCategoryRef>49</PoiCategoryRef>
			<!-- Bestuur en beheer -->
			<PoiCategoryRef>33</PoiCategoryRef>
			<!-- Bezienswaardigheden -->
			<PoiCategoryRef>34</PoiCategoryRef>
			<!-- Bioscopen -->
			<PoiCategoryRef>42</PoiCategoryRef>
			<!-- Bootsport -->
			<PoiCategoryRef>18</PoiCategoryRef>
			<!-- Busstations -->
			<PoiCategoryRef>26</PoiCategoryRef>
			<!-- Cafés -->
			<PoiCategoryRef>35</PoiCategoryRef>
			<!-- Casino's -->
			<PoiCategoryRef>48</PoiCategoryRef>
			<!-- Congrescentra -->
			<PoiCategoryRef>29</PoiCategoryRef>
			<!-- Elektronica -->
			<PoiCategoryRef>38</PoiCategoryRef>
			<!-- Gedenktekens -->
			<PoiCategoryRef>25</PoiCategoryRef>
			<!-- Geldautomaten -->
			<PoiCategoryRef>22</PoiCategoryRef>
			<!-- Geneeskundige diensten -->
			<PoiCategoryRef>53</PoiCategoryRef>
			<!-- Godshuizen -->
			<PoiCategoryRef>41</PoiCategoryRef>
			<!-- Golfsport -->
			<PoiCategoryRef>10</PoiCategoryRef>
			<!-- Grensovergangen -->
			<PoiCategoryRef>8</PoiCategoryRef>
			<!-- Hotels en motels -->
			<PoiCategoryRef>54</PoiCategoryRef>
			<!-- Kerkhoven -->
			<PoiCategoryRef>28</PoiCategoryRef>
			<!-- Kleding -->
			<PoiCategoryRef>134</PoiCategoryRef>
			<!-- Laadstations -->
			<PoiCategoryRef>136</PoiCategoryRef>
			<!-- LPG tankstation -->
			<PoiCategoryRef>37</PoiCategoryRef>
			<!-- Musea -->
			<PoiCategoryRef>31</PoiCategoryRef>
			<!-- Nachtleven -->
			<PoiCategoryRef>52</PoiCategoryRef>
			<!-- Onderwijsinstellingen -->
			<PoiCategoryRef>102</PoiCategoryRef>
			<!-- Parkeerplaatsen -->
			<PoiCategoryRef>32</PoiCategoryRef>
			<!-- Parken -->
			<PoiCategoryRef>20</PoiCategoryRef>
			<!-- Politie -->
			<PoiCategoryRef>46</PoiCategoryRef>
			<!-- Post -->
			<PoiCategoryRef>44</PoiCategoryRef>
			<!-- Pretparken -->
			<PoiCategoryRef>104</PoiCategoryRef>
			<!-- Restaurants -->
			<PoiCategoryRef>43</PoiCategoryRef>
			<!-- Skisport -->
			<PoiCategoryRef>39</PoiCategoryRef>
			<!-- Sportcentra -->
			<PoiCategoryRef>16</PoiCategoryRef>
			<!-- Stations -->
			<PoiCategoryRef>101</PoiCategoryRef>
			<!-- Tankstations -->
			<PoiCategoryRef>19</PoiCategoryRef>
			<!-- Toeristeninformatie -->
			<PoiCategoryRef>9</PoiCategoryRef>
			<!-- Veerboten en autotreinen -->
			<PoiCategoryRef>2</PoiCategoryRef>
			<!-- Vliegveld -->
			<PoiCategoryRef>11</PoiCategoryRef>
			<!-- VW dealers -->
			<PoiCategoryRef>12</PoiCategoryRef>
			<!-- VW service -->
			<PoiCategoryRef>7</PoiCategoryRef>
			<!-- Wegrestaurants -->
			<PoiCategoryRef>30</PoiCategoryRef>
			<!-- Wijnen en gedestilleerd -->
			<PoiCategoryRef>27</PoiCategoryRef>
			<!-- Winkelcentra -->
			<PoiCategoryRef>21</PoiCategoryRef>
			<!-- Ziekenhuis -->
		</PoiCategoryMapping>
		<PoiCategoryMapping fueltype="lpg">
			<PoiCategoryRef>135</PoiCategoryRef>
			<!-- Aardgas tankstations -->
			<PoiCategoryRef>50</PoiCategoryRef>
			<!-- Ambassades -->
			<PoiCategoryRef>23</PoiCategoryRef>
			<!-- Apotheken -->
			<PoiCategoryRef>1</PoiCategoryRef>
			<!-- Autostadt -->
			<PoiCategoryRef>15</PoiCategoryRef>
			<!-- Autoverhuur -->
			<PoiCategoryRef>14</PoiCategoryRef>
			<!-- Autowegaf-/opritten -->
			<PoiCategoryRef>45</PoiCategoryRef>
			<!-- Banken -->
			<PoiCategoryRef>47</PoiCategoryRef>
			<!-- Bedrijven -->
			<PoiCategoryRef>36</PoiCategoryRef>
			<!-- Beeldende kunsten -->
			<PoiCategoryRef>49</PoiCategoryRef>
			<!-- Bestuur en beheer -->
			<PoiCategoryRef>33</PoiCategoryRef>
			<!-- Bezienswaardigheden -->
			<PoiCategoryRef>34</PoiCategoryRef>
			<!-- Bioscopen -->
			<PoiCategoryRef>42</PoiCategoryRef>
			<!-- Bootsport -->
			<PoiCategoryRef>18</PoiCategoryRef>
			<!-- Busstations -->
			<PoiCategoryRef>26</PoiCategoryRef>
			<!-- Cafés -->
			<PoiCategoryRef>35</PoiCategoryRef>
			<!-- Casino's -->
			<PoiCategoryRef>48</PoiCategoryRef>
			<!-- Congrescentra -->
			<PoiCategoryRef>29</PoiCategoryRef>
			<!-- Elektronica -->
			<PoiCategoryRef>38</PoiCategoryRef>
			<!-- Gedenktekens -->
			<PoiCategoryRef>25</PoiCategoryRef>
			<!-- Geldautomaten -->
			<PoiCategoryRef>22</PoiCategoryRef>
			<!-- Geneeskundige diensten -->
			<PoiCategoryRef>53</PoiCategoryRef>
			<!-- Godshuizen -->
			<PoiCategoryRef>41</PoiCategoryRef>
			<!-- Golfsport -->
			<PoiCategoryRef>10</PoiCategoryRef>
			<!-- Grensovergangen -->
			<PoiCategoryRef>8</PoiCategoryRef>
			<!-- Hotels en motels -->
			<PoiCategoryRef>54</PoiCategoryRef>
			<!-- Kerkhoven -->
			<PoiCategoryRef>28</PoiCategoryRef>
			<!-- Kleding -->
			<PoiCategoryRef>134</PoiCategoryRef>
			<!-- Laadstations -->
			<PoiCategoryRef>136</PoiCategoryRef>
			<!-- LPG tankstation -->
			<PoiCategoryRef>37</PoiCategoryRef>
			<!-- Musea -->
			<PoiCategoryRef>31</PoiCategoryRef>
			<!-- Nachtleven -->
			<PoiCategoryRef>52</PoiCategoryRef>
			<!-- Onderwijsinstellingen -->
			<PoiCategoryRef>102</PoiCategoryRef>
			<!-- Parkeerplaatsen -->
			<PoiCategoryRef>32</PoiCategoryRef>
			<!-- Parken -->
			<PoiCategoryRef>20</PoiCategoryRef>
			<!-- Politie -->
			<PoiCategoryRef>46</PoiCategoryRef>
			<!-- Post -->
			<PoiCategoryRef>44</PoiCategoryRef>
			<!-- Pretparken -->
			<PoiCategoryRef>104</PoiCategoryRef>
			<!-- Restaurants -->
			<PoiCategoryRef>43</PoiCategoryRef>
			<!-- Skisport -->
			<PoiCategoryRef>39</PoiCategoryRef>
			<!-- Sportcentra -->
			<PoiCategoryRef>16</PoiCategoryRef>
			<!-- Stations -->
			<PoiCategoryRef>101</PoiCategoryRef>
			<!-- Tankstations -->
			<PoiCategoryRef>19</PoiCategoryRef>
			<!-- Toeristeninformatie -->
			<PoiCategoryRef>9</PoiCategoryRef>
			<!-- Veerboten en autotreinen -->
			<PoiCategoryRef>2</PoiCategoryRef>
			<!-- Vliegveld -->
			<PoiCategoryRef>11</PoiCategoryRef>
			<!-- VW dealers -->
			<PoiCategoryRef>12</PoiCategoryRef>
			<!-- VW service -->
			<PoiCategoryRef>7</PoiCategoryRef>
			<!-- Wegrestaurants -->
			<PoiCategoryRef>30</PoiCategoryRef>
			<!-- Wijnen en gedestilleerd -->
			<PoiCategoryRef>27</PoiCategoryRef>
			<!-- Winkelcentra -->
			<PoiCategoryRef>21</PoiCategoryRef>
			<!-- Ziekenhuis -->
		</PoiCategoryMapping>
		<PoiCategoryMapping fueltype="bev">
			<PoiCategoryRef>135</PoiCategoryRef>
			<!-- Aardgas tankstations -->
			<PoiCategoryRef>50</PoiCategoryRef>
			<!-- Ambassades -->
			<PoiCategoryRef>23</PoiCategoryRef>
			<!-- Apotheken -->
			<PoiCategoryRef>1</PoiCategoryRef>
			<!-- Autostadt -->
			<PoiCategoryRef>15</PoiCategoryRef>
			<!-- Autoverhuur -->
			<PoiCategoryRef>14</PoiCategoryRef>
			<!-- Autowegaf-/opritten -->
			<PoiCategoryRef>45</PoiCategoryRef>
			<!-- Banken -->
			<PoiCategoryRef>47</PoiCategoryRef>
			<!-- Bedrijven -->
			<PoiCategoryRef>36</PoiCategoryRef>
			<!-- Beeldende kunsten -->
			<PoiCategoryRef>49</PoiCategoryRef>
			<!-- Bestuur en beheer -->
			<PoiCategoryRef>33</PoiCategoryRef>
			<!-- Bezienswaardigheden -->
			<PoiCategoryRef>34</PoiCategoryRef>
			<!-- Bioscopen -->
			<PoiCategoryRef>42</PoiCategoryRef>
			<!-- Bootsport -->
			<PoiCategoryRef>18</PoiCategoryRef>
			<!-- Busstations -->
			<PoiCategoryRef>26</PoiCategoryRef>
			<!-- Cafés -->
			<PoiCategoryRef>35</PoiCategoryRef>
			<!-- Casino's -->
			<PoiCategoryRef>48</PoiCategoryRef>
			<!-- Congrescentra -->
			<PoiCategoryRef>29</PoiCategoryRef>
			<!-- Elektronica -->
			<PoiCategoryRef>38</PoiCategoryRef>
			<!-- Gedenktekens -->
			<PoiCategoryRef>25</PoiCategoryRef>
			<!-- Geldautomaten -->
			<PoiCategoryRef>22</PoiCategoryRef>
			<!-- Geneeskundige diensten -->
			<PoiCategoryRef>53</PoiCategoryRef>
			<!-- Godshuizen -->
			<PoiCategoryRef>41</PoiCategoryRef>
			<!-- Golfsport -->
			<PoiCategoryRef>10</PoiCategoryRef>
			<!-- Grensovergangen -->
			<PoiCategoryRef>8</PoiCategoryRef>
			<!-- Hotels en motels -->
			<PoiCategoryRef>54</PoiCategoryRef>
			<!-- Kerkhoven -->
			<PoiCategoryRef>28</PoiCategoryRef>
			<!-- Kleding -->
			<PoiCategoryRef>134</PoiCategoryRef>
			<!-- Laadstations -->
			<PoiCategoryRef>136</PoiCategoryRef>
			<!-- LPG tankstation -->
			<PoiCategoryRef>37</PoiCategoryRef>
			<!-- Musea -->
			<PoiCategoryRef>31</PoiCategoryRef>
			<!-- Nachtleven -->
			<PoiCategoryRef>52</PoiCategoryRef>
			<!-- Onderwijsinstellingen -->
			<PoiCategoryRef>102</PoiCategoryRef>
			<!-- Parkeerplaatsen -->
			<PoiCategoryRef>32</PoiCategoryRef>
			<!-- Parken -->
			<PoiCategoryRef>20</PoiCategoryRef>
			<!-- Politie -->
			<PoiCategoryRef>46</PoiCategoryRef>
			<!-- Post -->
			<PoiCategoryRef>44</PoiCategoryRef>
			<!-- Pretparken -->
			<PoiCategoryRef>104</PoiCategoryRef>
			<!-- Restaurants -->
			<PoiCategoryRef>43</PoiCategoryRef>
			<!-- Skisport -->
			<PoiCategoryRef>39</PoiCategoryRef>
			<!-- Sportcentra -->
			<PoiCategoryRef>16</PoiCategoryRef>
			<!-- Stations -->
			<PoiCategoryRef>101</PoiCategoryRef>
			<!-- Tankstations -->
			<PoiCategoryRef>19</PoiCategoryRef>
			<!-- Toeristeninformatie -->
			<PoiCategoryRef>9</PoiCategoryRef>
			<!-- Veerboten en autotreinen -->
			<PoiCategoryRef>2</PoiCategoryRef>
			<!-- Vliegveld -->
			<PoiCategoryRef>11</PoiCategoryRef>
			<!-- VW dealers -->
			<PoiCategoryRef>12</PoiCategoryRef>
			<!-- VW service -->
			<PoiCategoryRef>7</PoiCategoryRef>
			<!-- Wegrestaurants -->
			<PoiCategoryRef>30</PoiCategoryRef>
			<!-- Wijnen en gedestilleerd -->
			<PoiCategoryRef>27</PoiCategoryRef>
			<!-- Winkelcentra -->
			<PoiCategoryRef>21</PoiCategoryRef>
			<!-- Ziekenhuis -->
		</PoiCategoryMapping>
		<PoiCategoryMapping fueltype="phev">
			<PoiCategoryRef>135</PoiCategoryRef>
			<!-- Aardgas tankstations -->
			<PoiCategoryRef>50</PoiCategoryRef>
			<!-- Ambassades -->
			<PoiCategoryRef>23</PoiCategoryRef>
			<!-- Apotheken -->
			<PoiCategoryRef>1</PoiCategoryRef>
			<!-- Autostadt -->
			<PoiCategoryRef>15</PoiCategoryRef>
			<!-- Autoverhuur -->
			<PoiCategoryRef>14</PoiCategoryRef>
			<!-- Autowegaf-/opritten -->
			<PoiCategoryRef>45</PoiCategoryRef>
			<!-- Banken -->
			<PoiCategoryRef>47</PoiCategoryRef>
			<!-- Bedrijven -->
			<PoiCategoryRef>36</PoiCategoryRef>
			<!-- Beeldende kunsten -->
			<PoiCategoryRef>49</PoiCategoryRef>
			<!-- Bestuur en beheer -->
			<PoiCategoryRef>33</PoiCategoryRef>
			<!-- Bezienswaardigheden -->
			<PoiCategoryRef>34</PoiCategoryRef>
			<!-- Bioscopen -->
			<PoiCategoryRef>42</PoiCategoryRef>
			<!-- Bootsport -->
			<PoiCategoryRef>18</PoiCategoryRef>
			<!-- Busstations -->
			<PoiCategoryRef>26</PoiCategoryRef>
			<!-- Cafés -->
			<PoiCategoryRef>35</PoiCategoryRef>
			<!-- Casino's -->
			<PoiCategoryRef>48</PoiCategoryRef>
			<!-- Congrescentra -->
			<PoiCategoryRef>29</PoiCategoryRef>
			<!-- Elektronica -->
			<PoiCategoryRef>38</PoiCategoryRef>
			<!-- Gedenktekens -->
			<PoiCategoryRef>25</PoiCategoryRef>
			<!-- Geldautomaten -->
			<PoiCategoryRef>22</PoiCategoryRef>
			<!-- Geneeskundige diensten -->
			<PoiCategoryRef>53</PoiCategoryRef>
			<!-- Godshuizen -->
			<PoiCategoryRef>41</PoiCategoryRef>
			<!-- Golfsport -->
			<PoiCategoryRef>10</PoiCategoryRef>
			<!-- Grensovergangen -->
			<PoiCategoryRef>8</PoiCategoryRef>
			<!-- Hotels en motels -->
			<PoiCategoryRef>54</PoiCategoryRef>
			<!-- Kerkhoven -->
			<PoiCategoryRef>28</PoiCategoryRef>
			<!-- Kleding -->
			<PoiCategoryRef>134</PoiCategoryRef>
			<!-- Laadstations -->
			<PoiCategoryRef>136</PoiCategoryRef>
			<!-- LPG tankstation -->
			<PoiCategoryRef>37</PoiCategoryRef>
			<!-- Musea -->
			<PoiCategoryRef>31</PoiCategoryRef>
			<!-- Nachtleven -->
			<PoiCategoryRef>52</PoiCategoryRef>
			<!-- Onderwijsinstellingen -->
			<PoiCategoryRef>102</PoiCategoryRef>
			<!-- Parkeerplaatsen -->
			<PoiCategoryRef>32</PoiCategoryRef>
			<!-- Parken -->
			<PoiCategoryRef>20</PoiCategoryRef>
			<!-- Politie -->
			<PoiCategoryRef>46</PoiCategoryRef>
			<!-- Post -->
			<PoiCategoryRef>44</PoiCategoryRef>
			<!-- Pretparken -->
			<PoiCategoryRef>104</PoiCategoryRef>
			<!-- Restaurants -->
			<PoiCategoryRef>43</PoiCategoryRef>
			<!-- Skisport -->
			<PoiCategoryRef>39</PoiCategoryRef>
			<!-- Sportcentra -->
			<PoiCategoryRef>16</PoiCategoryRef>
			<!-- Stations -->
			<PoiCategoryRef>101</PoiCategoryRef>
			<!-- Tankstations -->
			<PoiCategoryRef>19</PoiCategoryRef>
			<!-- Toeristeninformatie -->
			<PoiCategoryRef>9</PoiCategoryRef>
			<!-- Veerboten en autotreinen -->
			<PoiCategoryRef>2</PoiCategoryRef>
			<!-- Vliegveld -->
			<PoiCategoryRef>11</PoiCategoryRef>
			<!-- VW dealers -->
			<PoiCategoryRef>12</PoiCategoryRef>
			<!-- VW service -->
			<PoiCategoryRef>7</PoiCategoryRef>
			<!-- Wegrestaurants -->
			<PoiCategoryRef>30</PoiCategoryRef>
			<!-- Wijnen en gedestilleerd -->
			<PoiCategoryRef>27</PoiCategoryRef>
			<!-- Winkelcentra -->
			<PoiCategoryRef>21</PoiCategoryRef>
			<!-- Ziekenhuis -->
		</PoiCategoryMapping>
	</SetupCategoryDefinition>
  <PoiCategoryGroupDefinition>
    <PoiCategoryGroup id="10" type="dynamic">
      <Priority>1</Priority>
      <PoiCategoryMapping>
        <!-- MUSS LEER BLEIBEN Ueber XSD checken !! -->
      </PoiCategoryMapping>
    </PoiCategoryGroup>

    <PoiCategoryGroup id="11" type="local">
      <Priority>2</Priority>
      <PoiCategoryMapping>
        <PoiCategoryRef>50</PoiCategoryRef>
        <!-- Ambassades -->
        <PoiCategoryRef>23</PoiCategoryRef>
        <!-- Apotheken -->
        <PoiCategoryRef>1</PoiCategoryRef>
        <!-- Autostadt -->
        <PoiCategoryRef>15</PoiCategoryRef>
        <!-- Autoverhuur -->
        <PoiCategoryRef>45</PoiCategoryRef>
        <!-- Banken -->
        <PoiCategoryRef>47</PoiCategoryRef>
        <!-- Bedrijven -->
        <PoiCategoryRef>54</PoiCategoryRef>
        <!-- Begraafplaatsen -->
        <PoiCategoryRef>34</PoiCategoryRef>
        <!-- Bioscopen -->
        <PoiCategoryRef>18</PoiCategoryRef>
        <!-- Bushaltes -->
        <PoiCategoryRef>26</PoiCategoryRef>
        <!-- Cafés -->
        <PoiCategoryRef>35</PoiCategoryRef>
        <!-- Casino's -->
        <PoiCategoryRef>48</PoiCategoryRef>
        <!-- Congrescentra -->
        <PoiCategoryRef>29</PoiCategoryRef>
        <!-- Elektronica -->
        <PoiCategoryRef>135</PoiCategoryRef>
        <!-- Erdgastankstellen -->
        <PoiCategoryRef>25</PoiCategoryRef>
        <!-- Geldautomaten -->
        <PoiCategoryRef>53</PoiCategoryRef>
        <!-- Godshuizen -->
        <PoiCategoryRef>41</PoiCategoryRef>
        <!-- Golfsport -->
        <PoiCategoryRef>10</PoiCategoryRef>
        <!-- Grensovergangen -->
        <PoiCategoryRef>8</PoiCategoryRef>
        <!-- Hotels en motels -->
        <PoiCategoryRef>28</PoiCategoryRef>
        <!-- Kleding -->
        <PoiCategoryRef>134</PoiCategoryRef>
        <!-- Laadstation -->
        <PoiCategoryRef>136</PoiCategoryRef>
        <!-- LPG tankstations -->
        <PoiCategoryRef>22</PoiCategoryRef>
        <!-- Medische diensten -->
        <PoiCategoryRef>38</PoiCategoryRef>
        <!-- Monumenten -->
        <PoiCategoryRef>37</PoiCategoryRef>
        <!-- Musea -->
        <PoiCategoryRef>31</PoiCategoryRef>
        <!-- Nachtleven -->
        <PoiCategoryRef>52</PoiCategoryRef>
        <!-- Onderwijsinstellingen -->
        <PoiCategoryRef>102</PoiCategoryRef>
        <!-- Parkeerplaatsen -->
        <PoiCategoryRef>32</PoiCategoryRef>
        <!-- Parken -->
        <PoiCategoryRef>36</PoiCategoryRef>
        <!-- Podiumkunsten -->
        <PoiCategoryRef>20</PoiCategoryRef>
        <!-- Politie -->
        <PoiCategoryRef>46</PoiCategoryRef>
        <!-- Post -->
        <PoiCategoryRef>44</PoiCategoryRef>
        <!-- Pretparken -->
        <PoiCategoryRef>49</PoiCategoryRef>
        <!-- Regering en bestuur -->
        <PoiCategoryRef>104</PoiCategoryRef>
        <!-- Restaurants -->
        <PoiCategoryRef>43</PoiCategoryRef>
        <!-- Skisport -->
        <PoiCategoryRef>14</PoiCategoryRef>
        <!-- Snelweg op- en afritten -->
        <PoiCategoryRef>39</PoiCategoryRef>
        <!-- Sportcentra -->
        <PoiCategoryRef>101</PoiCategoryRef>
        <!-- Tankstations -->
        <PoiCategoryRef>33</PoiCategoryRef>
        <!-- Toeristische bezienswaardigheden -->
        <PoiCategoryRef>16</PoiCategoryRef>
        <!-- Treinstations -->
        <PoiCategoryRef>9</PoiCategoryRef>
        <!-- Veerboten -->
        <PoiCategoryRef>2</PoiCategoryRef>
        <!-- Vliegvelden -->
        <PoiCategoryRef>19</PoiCategoryRef>
        <!-- VVV -->
        <PoiCategoryRef>11</PoiCategoryRef>
        <!-- VW dealers -->
        <PoiCategoryRef>12</PoiCategoryRef>
        <!-- VW Service -->
        <PoiCategoryRef>42</PoiCategoryRef>
        <!-- Watersport -->
        <PoiCategoryRef>7</PoiCategoryRef>
        <!-- Wegrestaurants -->
        <PoiCategoryRef>30</PoiCategoryRef>
        <!-- Wijnen en sterke dranken -->
        <PoiCategoryRef>27</PoiCategoryRef>
        <!-- Winkelcentra -->
        <PoiCategoryRef>21</PoiCategoryRef>
        <!-- Ziekenhuizen -->
      </PoiCategoryMapping>
    </PoiCategoryGroup>

    <PoiCategoryGroup id="12" type="local">
      <Priority>3</Priority>
      <PoiCategoryMapping>
        <PoiCategoryRef>15</PoiCategoryRef>
        <!-- Autoverhuur -->
        <PoiCategoryRef>18</PoiCategoryRef>
        <!-- Bushaltes -->
        <PoiCategoryRef>135</PoiCategoryRef>
        <!-- Erdgastankstellen -->
        <PoiCategoryRef>10</PoiCategoryRef>
        <!-- Grensovergangen -->
        <PoiCategoryRef>8</PoiCategoryRef>
        <!-- Hotels en motels -->
        <PoiCategoryRef>134</PoiCategoryRef>
        <!-- Laadstation -->
        <PoiCategoryRef>136</PoiCategoryRef>
        <!-- LPG tankstations -->
        <PoiCategoryRef>102</PoiCategoryRef>
        <!-- Parkeerplaatsen -->
        <PoiCategoryRef>14</PoiCategoryRef>
        <!-- Snelweg op- en afritten -->
        <PoiCategoryRef>101</PoiCategoryRef>
        <!-- Tankstations -->
        <PoiCategoryRef>16</PoiCategoryRef>
        <!-- Treinstations -->
        <PoiCategoryRef>9</PoiCategoryRef>
        <!-- Veerboten -->
        <PoiCategoryRef>2</PoiCategoryRef>
        <!-- Vliegvelden -->
        <PoiCategoryRef>19</PoiCategoryRef>
        <!-- VVV -->
        <PoiCategoryRef>11</PoiCategoryRef>
        <!-- VW dealers -->
        <PoiCategoryRef>12</PoiCategoryRef>
        <!-- VW Service -->
        <PoiCategoryRef>7</PoiCategoryRef>
        <!-- Wegrestaurants -->
      </PoiCategoryMapping>
    </PoiCategoryGroup>

    <PoiCategoryGroup id="13" type="local">
      <Priority>4</Priority>
      <PoiCategoryMapping>
        <PoiCategoryRef>50</PoiCategoryRef>
        <!-- Ambassades -->
        <PoiCategoryRef>45</PoiCategoryRef>
        <!-- Banken -->
        <PoiCategoryRef>47</PoiCategoryRef>
        <!-- Bedrijven -->
        <PoiCategoryRef>54</PoiCategoryRef>
        <!-- Begraafplaatsen -->
        <PoiCategoryRef>48</PoiCategoryRef>
        <!-- Congrescentra -->
        <PoiCategoryRef>53</PoiCategoryRef>
        <!-- Godshuizen -->
        <PoiCategoryRef>52</PoiCategoryRef>
        <!-- Onderwijsinstellingen -->
        <PoiCategoryRef>46</PoiCategoryRef>
        <!-- Post -->
        <PoiCategoryRef>49</PoiCategoryRef>
        <!-- Regering en bestuur -->
      </PoiCategoryMapping>
    </PoiCategoryGroup>

    <PoiCategoryGroup id="14" type="local">
      <Priority>5</Priority>
      <PoiCategoryMapping>
        <PoiCategoryRef>1</PoiCategoryRef>
        <!-- Autostadt -->
        <PoiCategoryRef>34</PoiCategoryRef>
        <!-- Bioscopen -->
        <PoiCategoryRef>35</PoiCategoryRef>
        <!-- Casino's -->
        <PoiCategoryRef>41</PoiCategoryRef>
        <!-- Golfsport -->
        <PoiCategoryRef>38</PoiCategoryRef>
        <!-- Monumenten -->
        <PoiCategoryRef>37</PoiCategoryRef>
        <!-- Musea -->
        <PoiCategoryRef>32</PoiCategoryRef>
        <!-- Parken -->
        <PoiCategoryRef>36</PoiCategoryRef>
        <!-- Podiumkunsten -->
        <PoiCategoryRef>44</PoiCategoryRef>
        <!-- Pretparken -->
        <PoiCategoryRef>43</PoiCategoryRef>
        <!-- Skisport -->
        <PoiCategoryRef>39</PoiCategoryRef>
        <!-- Sportcentra -->
        <PoiCategoryRef>33</PoiCategoryRef>
        <!-- Toeristische bezienswaardigheden -->
        <PoiCategoryRef>42</PoiCategoryRef>
        <!-- Watersport -->
      </PoiCategoryMapping>
    </PoiCategoryGroup>

    <PoiCategoryGroup id="15" type="local">
      <Priority>6</Priority>
      <PoiCategoryMapping>
        <PoiCategoryRef>26</PoiCategoryRef>
        <!-- Cafés -->
        <PoiCategoryRef>29</PoiCategoryRef>
        <!-- Elektronica -->
        <PoiCategoryRef>25</PoiCategoryRef>
        <!-- Geldautomaten -->
        <PoiCategoryRef>28</PoiCategoryRef>
        <!-- Kleding -->
        <PoiCategoryRef>31</PoiCategoryRef>
        <!-- Nachtleven -->
        <PoiCategoryRef>104</PoiCategoryRef>
        <!-- Restaurants -->
        <PoiCategoryRef>30</PoiCategoryRef>
        <!-- Wijnen en sterke dranken -->
        <PoiCategoryRef>27</PoiCategoryRef>
        <!-- Winkelcentra -->
      </PoiCategoryMapping>
    </PoiCategoryGroup>

    <PoiCategoryGroup id="16" type="local">
      <Priority>7</Priority>
      <PoiCategoryMapping>
        <PoiCategoryRef>23</PoiCategoryRef>
        <!-- Apotheken -->
        <PoiCategoryRef>22</PoiCategoryRef>
        <!-- Medische diensten -->
        <PoiCategoryRef>20</PoiCategoryRef>
        <!-- Politie -->
        <PoiCategoryRef>21</PoiCategoryRef>
        <!-- Ziekenhuizen -->
      </PoiCategoryMapping>
    </PoiCategoryGroup>

  </PoiCategoryGroupDefinition>

  <PoiCategoryGroupNameDefinition>
    <Name category_group_ref="10">Mijn bijzondere reisdoelen (Personal POI)</Name>
    <Name category_group_ref="11">Categorieën (alfabetisch)</Name>
    <Name category_group_ref="12">Auto en reizen</Name>
    <Name category_group_ref="13">Bedrijven en publieke instellingen</Name>
    <Name category_group_ref="14">Bezienswaardigheden en vrije tijd</Name>
    <Name category_group_ref="15">Eten en boodschappen</Name>
    <Name category_group_ref="16">Noodgevallen</Name>
  </PoiCategoryGroupNameDefinition>

	<PoiCategoryThesaurusDefinition>
		<Thesaurus category_ref="1">
			<Value>Autostadt</Value>
		</Thesaurus>
		<Thesaurus category_ref="2">
			<Value>Vliegveld</Value>
			<Value>Luchthaven</Value>
		</Thesaurus>
		<Thesaurus category_ref="136">
			<Value>LPG tankstation</Value>
			<Value>LPG</Value>
			<Value>Gas</Value>
			<Value>Tanken</Value>
			<Value>Tankstation</Value>
			<Value>Tankstations</Value>
		</Thesaurus>
		<Thesaurus category_ref="135">
			<Value>Aardgas tankstations</Value>
			<Value>Aardgas tankstation</Value>
			<Value>Aardgas</Value>
			<Value>Gas</Value>
			<Value>CNG</Value>
			<Value>Tanken</Value>
			<Value>Tankstation</Value>
			<Value>Tankstations</Value>
		</Thesaurus>
		<Thesaurus category_ref="101">
			<Value>Tankstations</Value>
			<Value>Tankstation</Value>
			<Value>Tanken</Value>
			<Value>Benzine</Value>
			<Value>Diesel</Value>
		</Thesaurus>
		<Thesaurus category_ref="102">
			<Value>Parkeerplaatsen</Value>
			<Value>Parkeerplaats</Value>
			<Value>Parkeren</Value>
		</Thesaurus>
		<Thesaurus category_ref="7">
			<Value>Wegrestaurants</Value>
			<Value>Wegrestaurant</Value>
			<Value>Rustplaats</Value>
			<Value>Plee</Value>
			<Value>Toilet</Value>
			<Value>Toiletten</Value>
			<Value>Rusten</Value>
		</Thesaurus>
		<Thesaurus category_ref="8">
			<Value>Hotels en motels</Value>
			<Value>Hotel</Value>
			<Value>Hotels</Value>
			<Value>Motel</Value>
			<Value>Motels</Value>
			<Value>Pension</Value>
			<Value>Pensions</Value>
			<Value>Slapen</Value>
		</Thesaurus>
		<Thesaurus category_ref="9">
			<Value>Veerboten en autotreinen</Value>
			<Value>Autotrein</Value>
			<Value>Autotreinen</Value>
			<Value>Veerboot</Value>
			<Value>Veerboten</Value>
			<Value>Veer</Value>
			<Value>Veren</Value>
		</Thesaurus>
		<Thesaurus category_ref="10">
			<Value>Grensovergangen</Value>
			<Value>Grensovergang</Value>
			<Value>Grens</Value>
			<Value>Grenzen</Value>
		</Thesaurus>
		<Thesaurus category_ref="11">
			<Value>VW dealers</Value>
			<Value>Dealer</Value>
			<Value>Dealer</Value>
			<Value>VW</Value>
			<Value>Volkswagen</Value>
		</Thesaurus>
		<Thesaurus category_ref="12">
			<Value>VW service</Value>
			<Value>Volkswagen</Value>
			<Value>Werkplaats</Value>
			<Value>Garage</Value>
			<Value>Service</Value>
			<Value>Garages</Value>
			<Value>Inspectie</Value>
			<Value>Inspecties</Value>
			<Value>Onderhoud</Value>
			<Value>Beurt</Value>
		</Thesaurus>
		<Thesaurus category_ref="14">
			<Value>Autowegaf-/opritten</Value>
			<Value>Afrit</Value>
			<Value>Afritten</Value>
			<Value>Oprit</Value>
			<Value>Opritten</Value>
			<Value>Uitrit</Value>
			<Value>Uitritten</Value>
		</Thesaurus>
		<Thesaurus category_ref="15">
			<Value>Autoverhuur</Value>
			<Value>Autohuur</Value>
			<Value>Huren</Value>
		</Thesaurus>
		<Thesaurus category_ref="16">
			<Value>Stations</Value>
			<Value>Station</Value>
			<Value>Trein</Value>
			<Value>Treinen</Value>
			<Value>Spoor</Value>
		</Thesaurus>
		<Thesaurus category_ref="18">
			<Value>Busstations</Value>
			<Value>Busstation</Value>
			<Value>Bus</Value>
			<Value>Bussen</Value>
			<Value>Bushalte</Value>
			<Value>Bushaltes</Value>
		</Thesaurus>
		<Thesaurus category_ref="19">
			<Value>Toeristeninformatie</Value>
			<Value>Toeristencentrum</Value>
		</Thesaurus>
		<Thesaurus category_ref="20">
			<Value>Politie</Value>
			<Value>Politie</Value>
			<Value>112</Value>
		</Thesaurus>
		<Thesaurus category_ref="21">
			<Value>Ziekenhuis</Value>
			<Value>Ziekenhuizen</Value>
			<Value>Hospitaal</Value>
			<Value>Hospitaals</Value>
			<Value>Kliniek</Value>
			<Value>Klinieken</Value>
			<Value>Noodgeval</Value>
			<Value>Noodgevallen</Value>
			<Value>Arts</Value>
			<Value>Artsen</Value>
			<Value>Dokter</Value>
			<Value>Dokters</Value>
			<Value>112</Value>
		</Thesaurus>
		<Thesaurus category_ref="22">
			<Value>Geneeskundige diensten</Value>
			<Value>Geneeskundige dienst</Value>
			<Value>Praktijk</Value>
			<Value>Arts</Value>
			<Value>Artsen</Value>
		</Thesaurus>
		<Thesaurus category_ref="23">
			<Value>Apotheken</Value>
			<Value>Apotheek</Value>
			<Value>Medicamenten</Value>
			<Value>Medicament</Value>
			<Value>Medicijn</Value>
			<Value>Medicijnen</Value>
		</Thesaurus>
		<Thesaurus category_ref="104">
			<Value>Restaurants</Value>
			<Value>Restaurant</Value>
			<Value>Eten</Value>
			<Value>Drinken</Value>
			<Value>Eethuis</Value>
			<Value>Eetgelegenheid</Value>
			<Value>Honger</Value>
			<Value>Dorst</Value>
		</Thesaurus>
		<Thesaurus category_ref="25">
			<Value>Geldautomaten</Value>
			<Value>Geldautomaat</Value>
			<Value>Geld</Value>
			<Value>Contant geld</Value>
			<Value>ATM</Value>
			<Value>EC</Value>
			<Value>Automaat</Value>
			<Value>Automaten</Value>
		</Thesaurus>
		<Thesaurus category_ref="26">
			<Value>Cafés</Value>
			<Value>Café</Value>
			<Value>Koffie</Value>
		</Thesaurus>
		<Thesaurus category_ref="27">
			<Value>Winkelcentra</Value>
			<Value>Winkelcentrum</Value>
			<Value>Shopping</Value>
			<Value>Shoppen</Value>
			<Value>Inkopen</Value>
			<Value>Kopen</Value>
			<Value>Warenhuis</Value>
			<Value>Warenhuizen</Value>
		</Thesaurus>
		<Thesaurus category_ref="28">
			<Value>Kleding</Value>
			<Value>KLeren</Value>
			<Value>Schoen</Value>
			<Value>Schoenen</Value>
		</Thesaurus>
		<Thesaurus category_ref="29">
			<Value>Elektronica</Value>
			<Value>Techniek</Value>
			<Value>Computers</Value>
		</Thesaurus>
		<Thesaurus category_ref="30">
			<Value>Wijnen en gedestilleerd</Value>
			<Value>Wijnkelder</Value>
			<Value>Wijn</Value>
			<Value>Wijnen</Value>
			<Value>Spirituosa</Value>
			<Value>Gedestilleerd</Value>
			<Value>Alcohol</Value>
		</Thesaurus>
		<Thesaurus category_ref="31">
			<Value>Nachtleven</Value>
			<Value>Bar</Value>
			<Value>Kroeg</Value>
			<Value>Kroegen</Value>
		</Thesaurus>
		<Thesaurus category_ref="32">
			<Value>Parken</Value>
			<Value>Park</Value>
		</Thesaurus>
		<Thesaurus category_ref="33">
			<Value>Bezienswaardigheden</Value>
			<Value>Bezienswaardigheid</Value>
			<Value>Attractie</Value>
			<Value>Attracties</Value>
		</Thesaurus>
		<Thesaurus category_ref="34">
			<Value>Bioscopen</Value>
			<Value>Bioscoop</Value>
		</Thesaurus>
		<Thesaurus category_ref="35">
			<Value>Casino's</Value>
			<Value>Casino</Value>
			<Value>Speelbank</Value>
			<Value>Speelbanken</Value>
		</Thesaurus>
		<Thesaurus category_ref="36">
			<Value>Beeldende kunsten</Value>
			<Value>Opera</Value>
			<Value>Theater</Value>
			<Value>Concert</Value>
			<Value>Musical</Value>
		</Thesaurus>
		<Thesaurus category_ref="37">
			<Value>Musea</Value>
			<Value>Museum</Value>
		</Thesaurus>
		<Thesaurus category_ref="38">
			<Value>Gedenktekens</Value>
			<Value>Gedenkteken</Value>
			<Value>Monument</Value>
			<Value>Monumenten</Value>
		</Thesaurus>
		<Thesaurus category_ref="39">
			<Value>Sportcentra</Value>
			<Value>Sportcentrum</Value>
			<Value>Stadion</Value>
			<Value>Stadions</Value>
		</Thesaurus>
		<Thesaurus category_ref="41">
			<Value>Golfsport</Value>
			<Value>Golf</Value>
		</Thesaurus>
		<Thesaurus category_ref="42">
			<Value>Bootsport</Value>
			<Value>Boot</Value>
			<Value>Boten</Value>
			<Value>Zeilen</Value>
		</Thesaurus>
		<Thesaurus category_ref="43">
			<Value>Skisport</Value>
			<Value>Skiën</Value>
			<Value>Sport</Value>
		</Thesaurus>
		<Thesaurus category_ref="44">
			<Value>Pretparken</Value>
			<Value>Pretpark</Value>
		</Thesaurus>
		<Thesaurus category_ref="45">
			<Value>Banken</Value>
			<Value>Bank</Value>
			<Value>Geld</Value>
		</Thesaurus>
		<Thesaurus category_ref="46">
			<Value>Post</Value>
			<Value>Brief</Value>
			<Value>Briefen</Value>
			<Value>Pakket</Value>
			<Value>Pakketten</Value>
		</Thesaurus>
		<Thesaurus category_ref="47">
			<Value>Bedrijven</Value>
			<Value>Bedrijf</Value>
			<Value>Firma</Value>
			<Value>Onderneming</Value>
		</Thesaurus>
		<Thesaurus category_ref="48">
			<Value>Congrescentra</Value>
			<Value>Congrescentrum</Value>
		</Thesaurus>
		<Thesaurus category_ref="49">
			<Value>Bestuur en beheer</Value>
			<Value>Raadhuis</Value>
			<Value>Bestuur</Value>
			<Value>Bestuur</Value>
			<Value>Overheid</Value>
		</Thesaurus>
		<Thesaurus category_ref="50">
			<Value>Ambassades</Value>
			<Value>Ambassade</Value>
			<Value>Consulaat</Value>
			<Value>Consulaten</Value>
		</Thesaurus>
		<Thesaurus category_ref="52">
			<Value>Onderwijsinstellingen</Value>
			<Value>School</Value>
			<Value>Scholen</Value>
			<Value>Universiteit</Value>
			<Value>Onderwijsinstelling</Value>
		</Thesaurus>
		<Thesaurus category_ref="53">
			<Value>Godshuizen</Value>
			<Value>Godshuis</Value>
			<Value>Moskee</Value>
			<Value>Moskeeën</Value>
			<Value>Kerk</Value>
			<Value>Kerken</Value>
			<Value>Synagoge</Value>
			<Value>Synagogen</Value>
			<Value>Klooster</Value>
			<Value>Kloosters</Value>
		</Thesaurus>
		<Thesaurus category_ref="54">
			<Value>Kerkhoven</Value>
			<Value>Kerkhof</Value>
		</Thesaurus>
		<Thesaurus category_ref="134">
			<Value>Laadstations</Value>
			<Value>Laadstation</Value>
			<Value>Laden</Value>
			<Value>Opladen</Value>
		</Thesaurus>
	</PoiCategoryThesaurusDefinition>

	<PoiCategoryNameDefinition>
		<Name category_ref="1">Autostadt</Name>
		<Name category_ref="2">Vliegveld</Name>
		<Name category_ref="136">LPG tankstation</Name>
		<Name category_ref="135">Aardgas tankstations</Name>
		<Name category_ref="101">Tankstations</Name>
		<Name category_ref="102">Parkeerplaatsen</Name>
		<Name category_ref="7">Wegrestaurants</Name>
		<Name category_ref="8">Hotels en motels</Name>
		<Name category_ref="9">Veerboten en autotreinen</Name>
		<Name category_ref="10">Grensovergangen</Name>
		<Name category_ref="11">VW dealers</Name>
		<Name category_ref="12">VW service</Name>
		<Name category_ref="14">Autowegaf-/opritten</Name>
		<Name category_ref="15">Autoverhuur</Name>
		<Name category_ref="16">Stations</Name>
		<Name category_ref="18">Busstations</Name>
		<Name category_ref="19">Toeristeninformatie</Name>
		<Name category_ref="20">Politie</Name>
		<Name category_ref="21">Ziekenhuis</Name>
		<Name category_ref="22">Geneeskundige diensten</Name>
		<Name category_ref="23">Apotheken</Name>
		<Name category_ref="104">Restaurants</Name>
		<Name category_ref="25">Geldautomaten</Name>
		<Name category_ref="26">Cafés</Name>
		<Name category_ref="27">Winkelcentra</Name>
		<Name category_ref="28">Kleding</Name>
		<Name category_ref="29">Elektronica</Name>
		<Name category_ref="30">Wijnen en gedestilleerd</Name>
		<Name category_ref="31">Nachtleven</Name>
		<Name category_ref="32">Parken</Name>
		<Name category_ref="33">Bezienswaardigheden</Name>
		<Name category_ref="34">Bioscopen</Name>
		<Name category_ref="35">Casino's</Name>
		<Name category_ref="36">Beeldende kunsten</Name>
		<Name category_ref="37">Musea</Name>
		<Name category_ref="38">Gedenktekens</Name>
		<Name category_ref="39">Sportcentra</Name>
		<Name category_ref="41">Golfsport</Name>
		<Name category_ref="42">Bootsport</Name>
		<Name category_ref="43">Skisport</Name>
		<Name category_ref="44">Pretparken</Name>
		<Name category_ref="45">Banken</Name>
		<Name category_ref="46">Post</Name>
		<Name category_ref="47">Bedrijven</Name>
		<Name category_ref="48">Congrescentra</Name>
		<Name category_ref="49">Bestuur en beheer</Name>
		<Name category_ref="50">Ambassades</Name>
		<Name category_ref="52">Onderwijsinstellingen</Name>
		<Name category_ref="53">Godshuizen</Name>
		<Name category_ref="54">Kerkhoven</Name>
		<Name category_ref="134">Laadstations</Name>
	</PoiCategoryNameDefinition>
</LanguagePoiConfiguration>
